ip_query_mcp/__init__.py
ip_query_mcp/__main__.py
ip_query_mcp/server.py
ip_query_mcp-0.1.1.dist-info/METADATA
ip_query_mcp-0.1.1.dist-info/WHEEL
ip_query_mcp-0.1.1.dist-info/entry_points.txt
ip_query_mcp-0.1.1.dist-info/RECORD
