Metadata-Version: 2.4
Name: ip-query-mcp
Version: 0.1.1
Summary: MCP server for querying public and private IP addresses with VPN detection
Project-URL: Homepage, https://github.com/yourusername/ip-query-mcp
Project-URL: Repository, https://github.com/yourusername/ip-query-mcp
Project-URL: Issues, https://github.com/yourusername/ip-query-mcp/issues
Author-email: Your Name <your.email@example.com>
License: MIT
Keywords: ip,mcp,network,query,vpn
Classifier: Development Status :: 3 - Alpha
Classifier: Intended Audience :: Developers
Classifier: License :: OSI Approved :: MIT License
Classifier: Programming Language :: Python :: 3
Classifier: Programming Language :: Python :: 3.10
Classifier: Programming Language :: Python :: 3.11
Classifier: Programming Language :: Python :: 3.12
Requires-Python: >=3.10
Requires-Dist: httpx>=0.27.0
Requires-Dist: mcp>=1.0.0
Requires-Dist: netifaces>=0.11.0
Provides-Extra: dev
Requires-Dist: pytest-asyncio>=0.21.0; extra == 'dev'
Requires-Dist: pytest>=7.0.0; extra == 'dev'
